{
  "documents": [
    {
      "paper_title": "1803.07828",
      "num_tables": 3,
      "tables": [
        {
          "table_id": "table_1",
          "page": 9,
          "evaluation": {
            "expected_rows": 5,
            "expected_cols": 5,
            "columns": [
              "Dataset",
              "AKSW-bib",
              "DBpedia 2015-10",
              "DBpedia 2016-04",
              ""
            ]
          },
          "rows": [
            [
              "Number of triples",
              3922,
              164369887,
              276316003,
              276316003
            ],
            [
              "Number of vectors",
              954,
              14921691,
              23816469,
              36596967
            ],
            [
              "Dimensionality",
              10,
              300,
              200,
              200
            ],
            [
              "Runtime (s)",
              2.2,
              18332,
              25380,
              46099
            ],
            [
              "Rate (triples/s)",
              1604,
              8966,
              10887,
              5994
            ]
          ]
        },
        {
          "table_id": "table_2",
          "page": 10,
          "evaluation": {
            "expected_rows": 4,
            "expected_cols": 3,
            "columns": [
              "Approach",
              "Steps",
              "Time"
            ]
          },
          "rows": [
            [
              "RDF2Vec",
              "Random walks generation Word2Vec training",
              "123 minutes >96 hours (*)"
            ],
            [
              "KGloVe",
              "Personalized PageRank Co-occurrence count matrix GloVe training",
              "N/A 12 hours (*)"
            ],
            [
              "KG2Vec",
              "Conversion to text Word2Vec training",
              "5 minutes 6 hours 58 minutes"
            ],
            [
              "fastText",
              "Conversion to text fastText training",
              "5 minutes >72 hours (*)"
            ]
          ]
        },
        {
          "table_id": "table_3",
          "page": 11,
          "evaluation": {
            "expected_rows": 3,
            "expected_cols": 4,
            "columns": [
              "",
              "Hits@1",
              "Hits@3",
              "Hits@10"
            ]
          },
          "rows": [
            [
              "LSTM + corrupted",
              "3.84%",
              "9.79%",
              "19.23%"
            ],
            [
              "LSTM + random",
              "1.39%",
              "4.89%",
              "10.49%"
            ],
            [
              "Analogy",
              "0.00%",
              "0.51%",
              "3.82%"
            ]
          ]
        }
      ]
    }
  ]
}